vigorvision/VISIONMODEL.py
vigorvision/__init__.py
vigorvision/trainseg.py
vigorvision/data/__init__.py
vigorvision/data/dataloader.py
vigorvision/data/segmentation_loader.py
vigorvision/engine/__init__.py
vigorvision/engine/evaluator.py
vigorvision/engine/inference.py
vigorvision/engine/trainer.py
vigorvision/engine/trainer_seg.py
vigorvision/engine/validator.py
vigorvision/models/__init__.py
vigorvision/models/build.py
vigorvision/models/model_config.py
vigorvision/models/vision/__init__.py
vigorvision/models/vision/segment.py
vigorvision/models/vision/visionmodel.py
vigorvision/nn/__init__.py
vigorvision/nn/loss.py
vigorvision/nn/module/__init__.py
vigorvision/nn/module/a2c2f.py
vigorvision/nn/module/c3k2.py
vigorvision/nn/module/c4k2.py
vigorvision/nn/module/conv.py
vigorvision/nn/module/custom_upsample.py
vigorvision/nn/module/detectionhead.py
vigorvision/nn/module/seblock.py
vigorvision/nn/module/vigorneck.py
vigorvision/utils/__init__.py
vigorvision/utils/autoanchor.py
vigorvision/utils/box_ops.py
vigorvision/utils/decoder.py
vigorvision/utils/encoder.py
vigorvision/utils/general.py
vigorvision/utils/iou.py
vigorvision/utils/metrics.py
vigorvision/utils/plotting.py
vigorvision/utils/predict.py
vigorvision/utils/transform_segmentation.py
vigorvision/utils/transforms.py
vigorvision-2.1.5.dist-info/METADATA
vigorvision-2.1.5.dist-info/WHEEL
vigorvision-2.1.5.dist-info/top_level.txt
vigorvision-2.1.5.dist-info/RECORD
