Metadata-Version: 2.4
Name: vigorvision
Version: 2.1.5
Summary: Advanced AI vision and object detection framework by Vigor Industries Limited.
Author-email: Vigor Industries Limited <contact@vigorindustries.com>
Keywords: deep-learning,object-detection,vision,AI,Vigor,torch,computer-vision,Vigor Infotech Limited,Vigor-Vision
Classifier: Development Status :: 4 - Beta
Classifier: Programming Language :: Python :: 3
Classifier: Programming Language :: Python :: 3.8
Classifier: Programming Language :: Python :: 3.9
Classifier: Programming Language :: Python :: 3.10
Classifier: Intended Audience :: Developers
Classifier: Topic :: Scientific/Engineering :: Artificial Intelligence
Classifier: License :: OSI Approved :: MIT License
Classifier: Operating System :: OS Independent
Requires-Python: >=3.8
Requires-Dist: torch>=2.0.1
Requires-Dist: torchvision>=0.15.0
Requires-Dist: albumentations>=1.3.0
Requires-Dist: opencv-python>=4.8.0
Requires-Dist: numpy>=1.24.0
Requires-Dist: matplotlib>=3.8.0
Requires-Dist: tqdm>=4.65.0
Requires-Dist: pyyaml>=6.0
Requires-Dist: scikit-learn>=1.3.0
Requires-Dist: scipy>=1.11.0
Requires-Dist: tensorboard>=2.13.0
Requires-Dist: wandb>=0.16.0
